numerator/__init__.py
numerator/cache.py
numerator/client.py
numerator/config.py
numerator/context.py
numerator/feature_flags.py
numerator/types.py
numerator/version.py
numeratorpy-0.0.3.dist-info/LICENSE
numeratorpy-0.0.3.dist-info/METADATA
numeratorpy-0.0.3.dist-info/WHEEL
numeratorpy-0.0.3.dist-info/top_level.txt
numeratorpy-0.0.3.dist-info/RECORD
