Metadata-Version: 2.1
Name: numeratorpy
Version: 0.0.3
Summary: Python SDK for Numerator Feature Management Platform
Author: Amos Zhang
Classifier: Programming Language :: Python :: 3
Classifier: Intended Audience :: Developers
Classifier: License :: OSI Approved :: Apache Software License
Classifier: Operating System :: OS Independent
Requires-Python: >=3.9
License-File: LICENSE
Requires-Dist: certifi ==2024.2.2
Requires-Dist: charset-normalizer ==3.3.2
Requires-Dist: idna ==3.6
Requires-Dist: requests ==2.31.0
Requires-Dist: urllib3 ==2.2.1
